{
  "Name": "Dynatrace HTTP Monitor",
  "FrequencyMin": 10,
  "Type": "HTTP",
  "Enabled": 123,
  "AnomalyDetection": {
    "OutageHandling": {
      "GlobalOutage": true,
      "GlobalOutagePolicy": {
        "ConsecutiveRuns": 2
      },
      "LocalOutage": true,
      "LocalOutagePolicy": {
        "AffectedLocations": 1,
        "ConsecutiveRuns": 3
      }
    },
    "LoadingTimeThresholds": {
      "Enabled": true,
      "Thresholds": [
        {
          "Type": "TOTAL",
          "ValueMs": 100
        }
      ]
    }
  },
  "Script": {},
  "Locations": [],
  "ManuallyAssignedApps": [],
  "ManagementZones": [],
  "Tags": [
    {
      "Source": "AUTO",
      "Context": "CONTEXTLESS",
      "Key": "Resource Type",
      "Value": "Dynatrace::Environment::SyntheticMonitor"
    }
  ]
}